LICENSE
MANIFEST.in
README.md
setup.py
adbui/__init__.py
adbui/adb_ext.py
adbui/get_ui.py
adbui/ocr.py
adbui/tango.py
adbui/util.py
adbui.egg-info/PKG-INFO
adbui.egg-info/SOURCES.txt
adbui.egg-info/dependency_links.txt
adbui.egg-info/requires.txt
adbui.egg-info/top_level.txt
adbui/static/adbui
tests/test_adb_ext.py
tests/test_util.py