Metadata-Version: 2.1
Name: adbui
Version: 4.5.20
Summary: adbui 所有的功能都是通过 adb 命令，adbui 的特色是可以通过 xpath，ocr 获取 ui 元素。
Home-page: https://github.com/hao1032/adbui
Author: Tango Nian
Author-email: hao1032@gmail.com
License: MIT
Keywords: testing android uiautomator ocr minicap
Platform: any
Classifier: Development Status :: 4 - Beta
Classifier: License :: OSI Approved :: MIT License
Classifier: Programming Language :: Python
Classifier: Programming Language :: Python :: 2
Classifier: Programming Language :: Python :: 3
Classifier: Topic :: Software Development :: Testing
License-File: LICENSE
Requires-Dist: lxml
Requires-Dist: requests
Requires-Dist: func_timeout
Requires-Dist: tencentcloud-sdk-python>=3.0.0
